opt/rtl/ksa.v
// =============================================================================
// Kogge-Stone Parallel Prefix Adder — 32-bit, parameterized WIDTH
// Supports addition AND subtraction (pass sub=1 to negate B via two's complement)
//
// Critical-path depth: O(log2 WIDTH) prefix levels instead of O(WIDTH) for RCA.
// For WIDTH=32: 5 prefix levels = ~5 XOR/AND gate delays on the carry path.
//
// Interface:
//   a    [WIDTH-1:0]  Operand A
//   b    [WIDTH-1:0]  Operand B
//   sub               When 1, computes A - B (i.e., A + ~B + 1)
//   sum  [WIDTH-1:0]  Result
//   cout              Carry-out (overflow detection for unsigned arithmetic)
// =============================================================================

`timescale 1ns/1ps

module ksa #(
    parameter WIDTH = 32
) (
    input  [WIDTH-1:0] a,
    input  [WIDTH-1:0] b,
    input              sub,   // 0→add, 1→subtract
    output [WIDTH-1:0] sum,
    output             cout
);

    // -------------------------------------------------------------------------
    // Pre-processing: Generate (G) and Propagate (P) signals per bit
    //   B is conditionally inverted for subtraction; carry-in is sub.
    // -------------------------------------------------------------------------
    wire [WIDTH-1:0] b_eff = b ^ {WIDTH{sub}};   // ~b when sub=1, b when sub=0

    wire [WIDTH-1:0] g0 = a & b_eff;              // bit-level generate
    wire [WIDTH-1:0] p0 = a ^ b_eff;              // bit-level propagate (also used as XOR sum bits)

    // -------------------------------------------------------------------------
    // Prefix network — Kogge-Stone topology
    // Each stage doubles the span of the carry look-ahead.
    // After log2(WIDTH) stages, G[i] contains the group-generate for bits [i:0],
    // which equals the carry INTO bit i+1.
    //
    // Naming:  g[stage][bit], p[stage][bit]
    //   g[k][i]  = carry generated for prefix [i .. 0]
    //   p[k][i]  = carry propagated  for prefix [i .. 0]
    // -------------------------------------------------------------------------
    localparam LEVELS = $clog2(WIDTH);   // 5 for WIDTH=32

    // Unpack into 2-D arrays via wires.
    // Verilog-2001 doesn't allow 2-D port arrays, so we use flat wire banks.
    wire [WIDTH-1:0] g [0:LEVELS];
    wire [WIDTH-1:0] p [0:LEVELS];

    assign g[0] = g0;
    assign p[0] = p0;

    genvar k, i;
    generate
        for (k = 0; k < LEVELS; k = k + 1) begin : PREFIX_STAGE
            localparam SPAN = 1 << k;   // 1,2,4,8,16 for k=0..4
            for (i = 0; i < WIDTH; i = i + 1) begin : BIT
                if (i >= SPAN) begin
                    // Black-cell (Kogge-Stone operator):
                    //   G[k+1][i] = G[k][i] | (P[k][i] & G[k][i-SPAN])
                    //   P[k+1][i] = P[k][i] & P[k][i-SPAN]
                    assign g[k+1][i] = g[k][i] | (p[k][i] & g[k][i-SPAN]);
                    assign p[k+1][i] = p[k][i] & p[k][i-SPAN];
                end else begin
                    // Buffer-cell: bit doesn't yet have a predecessor at this span
                    assign g[k+1][i] = g[k][i];
                    assign p[k+1][i] = p[k][i];
                end
            end
        end
    endgenerate

    // -------------------------------------------------------------------------
    // Post-processing: form final carry chain, then XOR with propagate bits
    //   carry[i]  = carry into position i
    //   carry[0]  = sub  (the initial carry-in of the two's-complement trick)
    //
    //   For i > 0:
    //     carry[i] = G_group[i-1] | (P_group[i-1] & cin)
    //
    //   where G_group and P_group are the full-prefix (group) signals from
    //   the Kogge-Stone tree covering bits [i-1:0].
    //   This correctly propagates the carry-in through long chains of
    //   generate=0, propagate=1 bits (e.g., -B when B=0).
    // -------------------------------------------------------------------------
    wire [WIDTH:0] carry;
    assign carry[0] = sub;
    genvar j;
    generate
        for (j = 1; j <= WIDTH; j = j + 1) begin : CARRY_OUT
            assign carry[j] = g[LEVELS][j-1] | (p[LEVELS][j-1] & sub);
        end
    endgenerate

    // Sum bit i = propagate[i] XOR carry[i]
    assign sum  = p0 ^ carry[WIDTH-1:0];
    assign cout = carry[WIDTH];

endmodule

opt/tb/tb_ksa.v
// =============================================================================
// tb_ksa.v — Comprehensive testbench for the 32-bit Kogge-Stone Adder
//
// Covers:
//   • ADD:  unsigned, signed, zero, max-value, random, overflow/carry-out
//   • SUB:  borrow, zero result, max-negative, random
//   • Edge cases: 0+0, MAX+1(→carry), 0-1(→borrow=carry-out from KSA)
//
// Compile & run:
//   iverilog -o tb_ksa tb_ksa.v ../rtl/ksa.v && ./tb_ksa
//   gtkwave dump_ksa.vcd &
// =============================================================================

`timescale 1ns/1ps

module tb_ksa;

    // -------------------------------------------------------------------------
    // DUT ports
    // -------------------------------------------------------------------------
    reg  [31:0] a;
    reg  [31:0] b;
    reg         sub;
    wire [31:0] sum;
    wire        cout;

    ksa #(.WIDTH(32)) dut (
        .a   (a),
        .b   (b),
        .sub (sub),
        .sum (sum),
        .cout(cout)
    );

    // -------------------------------------------------------------------------
    // Waveform dump
    // -------------------------------------------------------------------------
    initial begin
        $dumpfile("dump_ksa.vcd");
        $dumpvars(0, tb_ksa);
    end

    // -------------------------------------------------------------------------
    // Tracking
    // -------------------------------------------------------------------------
    integer pass_cnt = 0;
    integer fail_cnt = 0;

    task check_add;
        input [31:0] ta, tb_in;
        input        tsub;
        input [31:0] expect_sum;
        input        expect_cout;
        input [63:0] test_name_placeholder; // just a number
        reg   [32:0] full;
        begin
            a   = ta;
            b   = tb_in;
            sub = tsub;
            #5;  // propagation
            full = tsub ? ({1'b0,ta} + {1'b0,~tb_in} + 33'd1)
                        : ({1'b0,ta} + {1'b0, tb_in});
            if (sum !== expect_sum || cout !== expect_cout) begin
                $display("FAIL  a=%h b=%h sub=%b  got sum=%h cout=%b  want sum=%h cout=%b",
                         ta, tb_in, tsub, sum, cout, expect_sum, expect_cout);
                fail_cnt = fail_cnt + 1;
            end else begin
                pass_cnt = pass_cnt + 1;
            end
        end
    endtask

    // Self-checking task using Verilog arithmetic as oracle
    task auto_check;
        input [31:0] ta, tb_in;
        input        tsub;
        reg   [32:0] ref_full;
        reg   [31:0] ref_sum;
        reg          ref_cout;
        begin
            a   = ta;
            b   = tb_in;
            sub = tsub;
            #5;
            ref_full = tsub ? ({1'b0,ta} + {1'b0,~tb_in} + 33'd1)
                             : ({1'b0,ta} + {1'b0, tb_in});
            ref_sum  = ref_full[31:0];
            ref_cout = ref_full[32];
            if (sum !== ref_sum || cout !== ref_cout) begin
                $display("FAIL  a=%08h b=%08h sub=%b  got sum=%08h cout=%b  want sum=%08h cout=%b",
                         ta, tb_in, tsub, sum, cout, ref_sum, ref_cout);
                fail_cnt = fail_cnt + 1;
            end else begin
                pass_cnt = pass_cnt + 1;
            end
        end
    endtask

    // -------------------------------------------------------------------------
    // Random stimulus
    // -------------------------------------------------------------------------
    integer i;
    reg [31:0] randa, randb;

    initial begin
        $display("=====================================================");
        $display("  tb_ksa — Kogge-Stone Adder Testbench");
        $display("=====================================================");

        // --------- Directed ADD tests ----------------------------------------
        $display("\n[1] Directed ADD tests");

        // 0 + 0 = 0, no carry
        auto_check(32'h0000_0000, 32'h0000_0000, 1'b0);
        // 1 + 1 = 2
        auto_check(32'h0000_0001, 32'h0000_0001, 1'b0);
        // MAX + 0 = MAX
        auto_check(32'hFFFF_FFFF, 32'h0000_0000, 1'b0);
        // MAX + 1 = 0 with carry-out
        auto_check(32'hFFFF_FFFF, 32'h0000_0001, 1'b0);
        // MAX + MAX = 0xFFFFFFFE with carry-out
        auto_check(32'hFFFF_FFFF, 32'hFFFF_FFFF, 1'b0);
        // 0x5555_5555 + 0xAAAA_AAAA = 0xFFFF_FFFF
        auto_check(32'h5555_5555, 32'hAAAA_AAAA, 1'b0);
        // 0x8000_0000 + 0x8000_0000 = overflow → 0 + carry
        auto_check(32'h8000_0000, 32'h8000_0000, 1'b0);
        // Alternating patterns
        auto_check(32'hDEAD_BEEF, 32'h0102_0304, 1'b0);
        auto_check(32'hCAFE_BABE, 32'h0BAD_F00D, 1'b0);

        // --------- Directed SUB tests ----------------------------------------
        $display("[2] Directed SUB tests");

        // 0 - 0 = 0, no borrow (cout=1 means no borrow in two's complement)
        auto_check(32'h0000_0000, 32'h0000_0000, 1'b1);
        // 1 - 1 = 0
        auto_check(32'h0000_0001, 32'h0000_0001, 1'b1);
        // 0 - 1 = 0xFFFFFFFF (borrow, cout=0)
        auto_check(32'h0000_0000, 32'h0000_0001, 1'b1);
        // MAX - MAX = 0
        auto_check(32'hFFFF_FFFF, 32'hFFFF_FFFF, 1'b1);
        // MAX - 0 = MAX
        auto_check(32'hFFFF_FFFF, 32'h0000_0000, 1'b1);
        // 0x1000_0000 - 0x0FFF_FFFF = 1
        auto_check(32'h1000_0000, 32'h0FFF_FFFF, 1'b1);
        // Signed: negative result
        auto_check(32'h0000_0005, 32'h0000_000A, 1'b1);
        // 0x8000_0000 - 1 = 0x7FFF_FFFF
        auto_check(32'h8000_0000, 32'h0000_0001, 1'b1);
        // 0 - MAX = 1 (two's complement)
        auto_check(32'h0000_0000, 32'hFFFF_FFFF, 1'b1);
        // Sign boundary
        auto_check(32'h7FFF_FFFF, 32'h8000_0000, 1'b1);

        // --------- Random tests ----------------------------------------------
        $display("[3] Pseudo-random tests (1024 ADD + 1024 SUB)");
        randa = 32'hDEAD_BEEF;
        randb = 32'hCAFE_BABE;

        for (i = 0; i < 1024; i = i+1) begin
            // LFSR-style random
            randa = {randa[30:0], randa[31] ^ randa[21] ^ randa[1] ^ randa[0]};
            randb = {randb[30:0], randb[31] ^ randb[21] ^ randb[1] ^ randb[0]};
            auto_check(randa, randb, 1'b0);  // ADD
        end

        randa = 32'hABCD_EF01;
        randb = 32'h1234_5678;
        for (i = 0; i < 1024; i = i+1) begin
            randa = {randa[30:0], randa[31] ^ randa[21] ^ randa[1] ^ randa[0]};
            randb = {randb[30:0], randb[31] ^ randb[21] ^ randb[1] ^ randb[0]};
            auto_check(randa, randb, 1'b1);  // SUB
        end

        // --------- Carry-propagation stress ----------------------------------
        $display("[4] Carry-propagation patterns");
        // All bits set except LSB → adding 1 should produce carry chain
        auto_check(32'hFFFF_FFFE, 32'h0000_0001, 1'b0);
        auto_check(32'hFFFF_FFFC, 32'h0000_0003, 1'b0);
        auto_check(32'hFFFF_FFF0, 32'h0000_000F, 1'b0);
        auto_check(32'hFFFF_FF00, 32'h0000_00FF, 1'b0);
        auto_check(32'hFFFF_0000, 32'h0000_FFFF, 1'b0);
        auto_check(32'hFF00_0000, 32'h00FF_FFFF, 1'b0);
        auto_check(32'hF000_0000, 32'h0FFF_FFFF, 1'b0);
        auto_check(32'h8000_0000, 32'h7FFF_FFFF, 1'b0);

        // --------- Summary ----------------------------------------------------
        $display("\n=====================================================");
        $display("  Results: %0d PASSED   %0d FAILED", pass_cnt, fail_cnt);
        $display("=====================================================");
        if (fail_cnt == 0)
            $display("  ** ALL TESTS PASSED **");
        else
            $display("  ** FAILURES DETECTED — check output above **");

        $finish;
    end

    // Timeout watchdog
    initial #1_000_000 begin
        $display("TIMEOUT: simulation exceeded 1ms limit");
        $finish;
    end

endmodule

opt/build/dump_ksa.vcd
$date
	Sun Mar  8 12:03:27 2026
$end
$version
	Icarus Verilog
$end
$timescale
	1ps
$end
$scope module tb_ksa $end
$var wire 32 ! sum [31:0] $end
$var wire 1 " cout $end
$var reg 32 # a [31:0] $end
$var reg 32 $ b [31:0] $end
$var reg 32 % randa [31:0] $end
$var reg 32 & randb [31:0] $end
$var reg 1 ' sub $end
$var integer 32 ( fail_cnt [31:0] $end
$var integer 32 ) i [31:0] $end
$var integer 32 * pass_cnt [31:0] $end
$scope module dut $end
$var wire 32 + a [31:0] $end
$var wire 32 , b [31:0] $end
$var wire 32 - b_eff [31:0] $end
$var wire 32 . g0 [31:0] $end
$var wire 32 / p0 [31:0] $end
$var wire 1 ' sub $end
$var wire 32 0 sum [31:0] $end
$var wire 1 " cout $end
$var wire 33 1 carry [32:0] $end
$scope begin CARRY_OUT[1] $end
$upscope $end
$scope begin CARRY_OUT[2] $end
$upscope $end
$scope begin CARRY_OUT[3] $end
$upscope $end
$scope begin CARRY_OUT[4] $end
$upscope $end
$scope begin CARRY_OUT[5] $end
$upscope $end
$scope begin CARRY_OUT[6] $end
$upscope $end
$scope begin CARRY_OUT[7] $end
$upscope $end
$scope begin CARRY_OUT[8] $end
$upscope $end
$scope begin CARRY_OUT[9] $end
$upscope $end
$scope begin CARRY_OUT[10] $end
$upscope $end
$scope begin CARRY_OUT[11] $end
$upscope $end
$scope begin CARRY_OUT[12] $end
$upscope $end
$scope begin CARRY_OUT[13] $end
$upscope $end
$scope begin CARRY_OUT[14] $end
$upscope $end
$scope begin CARRY_OUT[15] $end
$upscope $end
$scope begin CARRY_OUT[16] $end
$upscope $end
$scope begin CARRY_OUT[17] $end
$upscope $end
$scope begin CARRY_OUT[18] $end
$upscope $end
$scope begin CARRY_OUT[19] $end
$upscope $end
$scope begin CARRY_OUT[20] $end
$upscope $end
$scope begin CARRY_OUT[21] $end
$upscope $end
$scope begin CARRY_OUT[22] $end
$upscope $end
$scope begin CARRY_OUT[23] $end
$upscope $end
$scope begin CARRY_OUT[24] $end
$upscope $end
$scope begin CARRY_OUT[25] $end
$upscope $end
$scope begin CARRY_OUT[26] $end
$upscope $end
$scope begin CARRY_OUT[27] $end
$upscope $end
$scope begin CARRY_OUT[28] $end
$upscope $end
$scope begin CARRY_OUT[29] $end
$upscope $end
$scope begin CARRY_OUT[30] $end
$upscope $end
$scope begin CARRY_OUT[31] $end
$upscope $end
$scope begin CARRY_OUT[32] $end
$upscope $end
$scope begin PREFIX_STAGE[0] $end
$scope begin BIT[0] $end
$scope begin genblk4 $end
$upscope $end
$upscope $end
$scope begin BIT[1] $end
$scope begin genblk3 $end
$upscope $end
$upscope $end
$scope begin BIT[2] $end
$scope begin genblk3 $end
$upscope $end
$upscope $end
$scope begin BIT[3] $end
$scope begin genblk3 $end
$upscope $end
$upscope $end
$scope begin BIT[4] $end
$scope begin genblk3 $end
$upscope $end
$upscope $end
$scope begin BIT[5] $end
$scope begin genblk3 $end
$upscope $end
$upscope $end
$scope begin BIT[6] $end
$scope begin genblk3 $end
$upscope $end
$upscope $end
$scope begin BIT[7] $end
$scope begin genblk3 $end
$upscope $end
$upscope $end
$scope begin BIT[8] $end
$scope begin genblk3 $end
$upscope $end
$upscope $end
$scope begin BIT[9] $end
$scope begin genblk3 $end
$upscope $end
$upscope $end
$scope begin BIT[10] $end
$scope begin genblk3 $end
$upscope $end
$upscope $end
$scope begin BIT[11] $end
$scope begin genblk3 $end
$upscope $end
$upscope $end
$scope begin BIT[12] $end
$scope begin genblk3 $end
$upscope $end
$upscope $end
$scope begin BIT[13] $end
$scope begin genblk3 $end
$upscope $end
$upscope $end
$scope begin BIT[14] $end
$scope begin genblk3 $end
$upscope $end
$upscope $end
$scope begin BIT[15] $end
$scope begin genblk3 $end
$upscope $end
$upscope $end
$scope begin BIT[16] $end
$scope begin genblk3 $end
$upscope $end
$upscope $end
$scope begin BIT[17] $end
$scope begin genblk3 $end
$upscope $end
$upscope $end
$scope begin BIT[18] $end
$scope begin genblk3 $end
$upscope $end
$upscope $end
$scope begin BIT[19] $end
$scope begin genblk3 $end
$upscope $end
$upscope $end
$scope begin BIT[20] $end
$scope begin genblk3 $end
$upscope $end
$upscope $end
$scope begin BIT[21] $end
$scope begin genblk3 $end
$upscope $end
$upscope $end
$scope begin BIT[22] $end
$scope begin genblk3 $end
$upscope $end
$upscope $end
$scope begin BIT[23] $end
$scope begin genblk3 $end
$upscope $end
$upscope $end
$scope begin BIT[24] $end
$scope begin genblk3 $end
$upscope $end
$upscope $end
$scope begin BIT[25] $end
$scope begin genblk3 $end
$upscope $end
$upscope $end
$scope begin BIT[26] $end
$scope begin genblk3 $end
$upscope $end
$upscope $end
$scope begin BIT[27] $end
$scope begin genblk3 $end
$upscope $end
$upscope $end
$scope begin BIT[28] $end
$scope begin genblk3 $end
$upscope $end
$upscope $end
$scope begin BIT[29] $end
$scope begin genblk3 $end
$upscope $end
$upscope $end
$scope begin BIT[30] $end
$scope begin genblk3 $end
$upscope $end
$upscope $end
$scope begin BIT[31] $end
$scope begin genblk3 $end
$upscope $end
$upscope $end
$upscope $end
$scope begin PREFIX_STAGE[1] $end
$scope begin BIT[0] $end
$scope begin genblk4 $end
$upscope $end
$upscope $end
$scope begin BIT[1] $end
$scope begin genblk4 $end
$upscope $end
$upscope $end
$scope begin BIT[2] $end
$scope begin genblk3 $end
$upscope $end
$upscope $end
$scope begin BIT[3] $end
$scope begin genblk3 $end
$upscope $end
$upscope $end
$scope begin BIT[4] $end
$scope begin genblk3 $end
$upscope $end
$upscope $end
$scope begin BIT[5] $end
$scope begin genblk3 $end
$upscope $end
$upscope $end
$scope begin BIT[6] $end
$scope begin genblk3 $end
$upscope $end
$upscope $end
$scope begin BIT[7] $end
$scope begin genblk3 $end
$upscope $end
$upscope $end
$scope begin BIT[8] $end
$scope begin genblk3 $end
$upscope $end
$upscope $end
$scope begin BIT[9] $end
$scope begin genblk3 $end
$upscope $end
$upscope $end
$scope begin BIT[10] $end
$scope begin genblk3 $end
$upscope $end
$upscope $end
$scope begin BIT[11] $end
$scope begin genblk3 $end
$upscope $end
$upscope $end
$scope begin BIT[12] $end
$scope begin genblk3 $end
$upscope $end
$upscope $end
$scope begin BIT[13] $end
$scope begin genblk3 $end
$upscope $end
$upscope $end
$scope begin BIT[14] $end
$scope begin genblk3 $end
$upscope $end
$upscope $end
$scope begin BIT[15] $end
$scope begin genblk3 $end
$upscope $end
$upscope $end
$scope begin BIT[16] $end
$scope begin genblk3 $end
$upscope $end
$upscope $end
$scope begin BIT[17] $end
$scope begin genblk3 $end
$upscope $end
$upscope $end
$scope begin BIT[18] $end
$scope begin genblk3 $end
$upscope $end
$upscope $end
$scope begin BIT[19] $end
$scope begin genblk3 $end
$upscope $end
$upscope $end
$scope begin BIT[20] $end
$scope begin genblk3 $end
$upscope $end
$upscope $end
$scope begin BIT[21] $end
$scope begin genblk3 $end
$upscope $end
$upscope $end
$scope begin BIT[22] $end
$scope begin genblk3 $end
$upscope $end
$upscope $end
$scope begin BIT[23] $end
$scope begin genblk3 $end
$upscope $end
$upscope $end
$scope begin BIT[24] $end
$scope begin genblk3 $end
$upscope $end
$upscope $end
$scope begin BIT[25] $end
$scope begin genblk3 $end
$upscope $end
$upscope $end
$scope begin BIT[26] $end
$scope begin genblk3 $end
$upscope $end
$upscope $end
$scope begin BIT[27] $end
$scope begin genblk3 $end
$upscope $end
$upscope $end
$scope begin BIT[28] $end
$scope begin genblk3 $end
$upscope $end
$upscope $end
$scope begin BIT[29] $end
$scope begin genblk3 $end
$upscope $end
$upscope $end
$scope begin BIT[30] $end
$scope begin genblk3 $end
$upscope $end
$upscope $end
$scope begin BIT[31] $end
$scope begin genblk3 $end
$upscope $end
$upscope $end
$upscope $end
$scope begin PREFIX_STAGE[2] $end
$scope begin BIT[0] $end
$scope begin genblk4 $end
$upscope $end
$upscope $end
$scope begin BIT[1] $end
$scope begin genblk4 $end
$upscope $end
$upscope $end
$scope begin BIT[2] $end
$scope begin genblk4 $end
$upscope $end
$upscope $end
$scope begin BIT[3] $end
$scope begin genblk4 $end
$upscope $end
$upscope $end
$scope begin BIT[4] $end
$scope begin genblk3 $end
$upscope $end
$upscope $end
$scope begin BIT[5] $end
$scope begin genblk3 $end
$upscope $end
$upscope $end
$scope begin BIT[6] $end
$scope begin genblk3 $end
$upscope $end
$upscope $end
$scope begin BIT[7] $end
$scope begin genblk3 $end
$upscope $end
$upscope $end
$scope begin BIT[8] $end
$scope begin genblk3 $end
$upscope $end
$upscope $end
$scope begin BIT[9] $end
$scope begin genblk3 $end
$upscope $end
$upscope $end
$scope begin BIT[10] $end
$scope begin genblk3 $end
$upscope $end
$upscope $end
$scope begin BIT[11] $end
$scope begin genblk3 $end
$upscope $end
$upscope $end
$scope begin BIT[12] $end
$scope begin genblk3 $end
$upscope $end
$upscope $end
$scope begin BIT[13] $end
$scope begin genblk3 $end
$upscope $end
$upscope $end
$scope begin BIT[14] $end
$scope begin genblk3 $end
$upscope $end
$upscope $end
$scope begin BIT[15] $end
$scope begin genblk3 $end
$upscope $end
$upscope $end
$scope begin BIT[16] $end
$scope begin genblk3 $end
$upscope $end
$upscope $end
$scope begin BIT[17] $end
$scope begin genblk3 $end
$upscope $end
$upscope $end
$scope begin BIT[18] $end
$scope begin genblk3 $end
$upscope $end
$upscope $end
$scope begin BIT[19] $end
$scope begin genblk3 $end
$upscope $end
$upscope $end
$scope begin BIT[20] $end
$scope begin genblk3 $end
$upscope $end
$upscope $end
$scope begin BIT[21] $end
$scope begin genblk3 $end
$upscope $end
$upscope $end
$scope begin BIT[22] $end
$scope begin genblk3 $end
$upscope $end
$upscope $end
$scope begin BIT[23] $end
$scope begin genblk3 $end
$upscope $end
$upscope $end
$scope begin BIT[24] $end
$scope begin genblk3 $end
$upscope $end
$upscope $end
$scope begin BIT[25] $end
$scope begin genblk3 $end
$upscope $end
$upscope $end
$scope begin BIT[26] $end
$scope begin genblk3 $end
$upscope $end
$upscope $end
$scope begin BIT[27] $end
$scope begin genblk3 $end
$upscope $end
$upscope $end
$scope begin BIT[28] $end
$scope begin genblk3 $end
$upscope $end
$upscope $end
$scope begin BIT[29] $end
$scope begin genblk3 $end
$upscope $end
$upscope $end
$scope begin BIT[30] $end
$scope begin genblk3 $end
$upscope $end
$upscope $end
$scope begin BIT[31] $end
$scope begin genblk3 $end
$upscope $end
$upscope $end
$upscope $end
$scope begin PREFIX_STAGE[3] $end
$scope begin BIT[0] $end
$scope begin genblk4 $end
$upscope $end
$upscope $end
$scope begin BIT[1] $end
$scope begin genblk4 $end
$upscope $end
$upscope $end
$scope begin BIT[2] $end
$scope begin genblk4 $end
$upscope $end
$upscope $end
$scope begin BIT[3] $end
$scope begin genblk4 $end
$upscope $end
$upscope $end
$scope begin BIT[4] $end
$scope begin genblk4 $end
$upscope $end
$upscope $end
$scope begin BIT[5] $end
$scope begin genblk4 $end
$upscope $end
$upscope $end
$scope begin BIT[6] $end
$scope begin genblk4 $end
$upscope $end
$upscope $end
$scope begin BIT[7] $end
$scope begin genblk4 $end
$upscope $end
$upscope $end
$scope begin BIT[8] $end
$scope begin genblk3 $end
$upscope $end
$upscope $end
$scope begin BIT[9] $end
$scope begin genblk3 $end
$upscope $end
$upscope $end
$scope begin BIT[10] $end
$scope begin genblk3 $end
$upscope $end
$upscope $end
$scope begin BIT[11] $end
$scope begin genblk3 $end
$upscope $end
$upscope $end
$scope begin BIT[12] $end
$scope begin genblk3 $end
$upscope $end
$upscope $end
$scope begin BIT[13] $end
$scope begin genblk3 $end
$upscope $end
$upscope $end
$scope begin BIT[14] $end
$scope begin genblk3 $end
$upscope $end
$upscope $end
$scope begin BIT[15] $end
$scope begin genblk3 $end
$upscope $end
$upscope $end
$scope begin BIT[16] $end
$scope begin genblk3 $end
$upscope $end
$upscope $end
$scope begin BIT[17] $end
$scope begin genblk3 $end
$upscope $end
$upscope $end
$scope begin BIT[18] $end
$scope begin genblk3 $end
$upscope $end
$upscope $end
$scope begin BIT[19] $end
$scope begin genblk3 $end
$upscope $end
$upscope $end
$scope begin BIT[20] $end
$scope begin genblk3 $end
$upscope $end
$upscope $end
$scope begin BIT[21] $end
$scope begin genblk3 $end
$upscope $end
$upscope $end
$scope begin BIT[22] $end
$scope begin genblk3 $end
$upscope $end
$upscope $end
$scope begin BIT[23] $end
$scope begin genblk3 $end
$upscope $end
$upscope $end
$scope begin BIT[24] $end
$scope begin genblk3 $end
$upscope $end
$upscope $end
$scope begin BIT[25] $end
$scope begin genblk3 $end
$upscope $end
$upscope $end
$scope begin BIT[26] $end
$scope begin genblk3 $end
$upscope $end
$upscope $end
$scope begin BIT[27] $end
$scope begin genblk3 $end
$upscope $end
$upscope $end
$scope begin BIT[28] $end
$scope begin genblk3 $end
$upscope $end
$upscope $end
$scope begin BIT[29] $end
$scope begin genblk3 $end
$upscope $end
$upscope $end
$scope begin BIT[30] $end
$scope begin genblk3 $end
$upscope $end
$upscope $end
$scope begin BIT[31] $end
$scope begin genblk3 $end
$upscope $end
$upscope $end
$upscope $end
$scope begin PREFIX_STAGE[4] $end
$scope begin BIT[0] $end
$scope begin genblk4 $end
$upscope $end
$upscope $end
$scope begin BIT[1] $end
$scope begin genblk4 $end
$upscope $end
$upscope $end
$scope begin BIT[2] $end
$scope begin genblk4 $end
$upscope $end
$upscope $end
$scope begin BIT[3] $end
$scope begin genblk4 $end
$upscope $end
$upscope $end
$scope begin BIT[4] $end
$scope begin genblk4 $end
$upscope $end
$upscope $end
$scope begin BIT[5] $end
$scope begin genblk4 $end
$upscope $end
$upscope $end
$scope begin BIT[6] $end
$scope begin genblk4 $end
$upscope $end
$upscope $end
$scope begin BIT[7] $end
$scope begin genblk4 $end
$upscope $end
$upscope $end
$scope begin BIT[8] $end
$scope begin genblk4 $end
$upscope $end
$upscope $end
$scope begin BIT[9] $end
$scope begin genblk4 $end
$upscope $end
$upscope $end
$scope begin BIT[10] $end
$scope begin genblk4 $end
$upscope $end
$upscope $end
$scope begin BIT[11] $end
$scope begin genblk4 $end
$upscope $end
$upscope $end
$scope begin BIT[12] $end
$scope begin genblk4 $end
$upscope $end
$upscope $end
$scope begin BIT[13] $end
$scope begin genblk4 $end
$upscope $end
$upscope $end
$scope begin BIT[14] $end
$scope begin genblk4 $end
$upscope $end
$upscope $end
$scope begin BIT[15] $end
$scope begin genblk4 $end
$upscope $end
$upscope $end
$scope begin BIT[16] $end
$scope begin genblk3 $end
$upscope $end
$upscope $end
$scope begin BIT[17] $end
$scope begin genblk3 $end
$upscope $end
$upscope $end
$scope begin BIT[18] $end
$scope begin genblk3 $end
$upscope $end
$upscope $end
$scope begin BIT[19] $end
$scope begin genblk3 $end
$upscope $end
$upscope $end
$scope begin BIT[20] $end
$scope begin genblk3 $end
$upscope $end
$upscope $end
$scope begin BIT[21] $end
$scope begin genblk3 $end
$upscope $end
$upscope $end
$scope begin BIT[22] $end
$scope begin genblk3 $end
$upscope $end
$upscope $end
$scope begin BIT[23] $end
$scope begin genblk3 $end
$upscope $end
$upscope $end
$scope begin BIT[24] $end
$scope begin genblk3 $end
$upscope $end
$upscope $end
$scope begin BIT[25] $end
$scope begin genblk3 $end
$upscope $end
$upscope $end
$scope begin BIT[26] $end
$scope begin genblk3 $end
$upscope $end
$upscope $end
$scope begin BIT[27] $end
$scope begin genblk3 $end
$upscope $end
$upscope $end
$scope begin BIT[28] $end
$scope begin genblk3 $end
$upscope $end
$upscope $end
$scope begin BIT[29] $end
$scope begin genblk3 $end
$upscope $end
$upscope $end
$scope begin BIT[30] $end
$scope begin genblk3 $end
$upscope $end
$upscope $end
$scope begin BIT[31] $end
$scope begin genblk3 $end
$upscope $end
$upscope $end
$upscope $end
$upscope $end
$scope task auto_check $end
$var reg 1 2 ref_cout $end
$var reg 33 3 ref_full [32:0] $end
$var reg 32 4 ref_sum [31:0] $end
$var reg 32 5 ta [31:0] $end
$var reg 32 6 tb_in [31:0] $end
$var reg 1 7 tsub $end
$upscope $end
$scope task check_add $end
$var reg 1 8 expect_cout $end
$var reg 32 9 expect_sum [31:0] $end
$var reg 33 : full [32:0] $end
$var reg 32 ; ta [31:0] $end
$var reg 32 < tb_in [31:0] $end
$var reg 64 = test_name_placeholder [63:0] $end
$var reg 1 > tsub $end
$upscope $end
$upscope $end
$enddefinitions $end
#0
$dumpvars
x>
bx =
bx <
bx ;
bx :
bx 9
x8
07
b0 6
b0 5
bx 4
bx 3
x2
b0 1
b0 0
b0 /
b0 .
b0 -
b0 ,
b0 +
b0 *
bx )
b0 (
0'
bx &
bx %
b0 $
b0 #
0"
b0 !
$end
#5000
b10 1
b1 .
b10 !
b10 0
b1 -
b0 /
b1 $
b1 ,
b1 #
b1 +
b1 6
b1 5
b1 *
02
b0 4
b0 3
#10000
0"
b0 1
b0 .
b11111111111111111111111111111111 !
b11111111111111111111111111111111 0
b0 -
b11111111111111111111111111111111 /
b0 $
b0 ,
b11111111111111111111111111111111 #
b11111111111111111111111111111111 +
b0 6
b11111111111111111111111111111111 5
b10 *
b10 4
b10 3
#15000
1"
b111111111111111111111111111111110 1
b0 !
b0 0
b1 .
b11111111111111111111111111111110 /
b1 -
b1 $
b1 ,
b1 6
b11 *
b11111111111111111111111111111111 4
b11111111111111111111111111111111 3
#20000
b11111111111111111111111111111110 !
b11111111111111111111111111111110 0
b11111111111111111111111111111111 .
b0 /
b11111111111111111111111111111111 -
b11111111111111111111111111111111 $
b11111111111111111111111111111111 ,
b11111111111111111111111111111111 6
b100 *
12
b0 4
b100000000000000000000000000000000 3
#25000
0"
b0 1
b11111111111111111111111111111111 !
b11111111111111111111111111111111 0
b10101010101010101010101010101010 -
b0 .
b11111111111111111111111111111111 /
b10101010101010101010101010101010 $
b10101010101010101010101010101010 ,
b1010101010101010101010101010101 #
b1010101010101010101010101010101 +
b10101010101010101010101010101010 6
b1010101010101010101010101010101 5
b101 *
b11111111111111111111111111111110 4
b111111111111111111111111111111110 3
#30000
1"
b100000000000000000000000000000000 1
b0 !
b0 0
b10000000000000000000000000000000 -
b10000000000000000000000000000000 .
b0 /
b10000000000000000000000000000000 $
b10000000000000000000000000000000 ,
b10000000000000000000000000000000 #
b10000000000000000000000000000000 +
b10000000000000000000000000000000 6
b10000000000000000000000000000000 5
b110 *
02
b11111111111111111111111111111111 4
b11111111111111111111111111111111 3
#35000
0"
b111110000011000 1
b1000000100 .
b11011111101011111100000111110011 !
b11011111101011111100000111110011 0
b1000000100000001100000100 -
b11011111101011111011110111101011 /
b1000000100000001100000100 $
b1000000100000001100000100 ,
b11011110101011011011111011101111 #
b11011110101011011011111011101111 +
b1000000100000001100000100 6
b11011110101011011011111011101111 5
b111 *
12
b0 4
b100000000000000000000000000000000 3
